welltest/__init__.py
welltest/functions.py
welltest-0.5.dist-info/METADATA
welltest-0.5.dist-info/WHEEL
welltest-0.5.dist-info/licenses/LICENSE
welltest-0.5.dist-info/RECORD
